LICENSE
README.md
setup.py
CytoSig/CytoSig_run.py
CytoSig/Util.py
CytoSig/__init__.py
CytoSig/signature.centroid
CytoSig/signature.centroid.beta
CytoSig/signature.centroid.expand
CytoSig.egg-info/PKG-INFO
CytoSig.egg-info/SOURCES.txt
CytoSig.egg-info/dependency_links.txt
CytoSig.egg-info/requires.txt
CytoSig.egg-info/top_level.txt
tests/__init__.py
tests/prediction.py