Metadata-Version: 2.1
Name: CytoSig
Version: 0.0.3
Summary: Prediction model for cytokine signaling activity
Home-page: https://github.com/data2intelligence/CytoSig
Author: Peng Jiang
Author-email: peng.jiang@nih.gov
Classifier: Programming Language :: Python :: 3
Classifier: License :: OSI Approved :: GNU General Public License v3 (GPLv3)
Classifier: Operating System :: OS Independent
Requires-Python: >=3.6
License-File: LICENSE
